center_tk_window.py
center_tk_window-1.0.0.dist-info/METADATA
center_tk_window-1.0.0.dist-info/WHEEL
center_tk_window-1.0.0.dist-info/license.txt
center_tk_window-1.0.0.dist-info/top_level.txt
center_tk_window-1.0.0.dist-info/RECORD
