Metadata-Version: 2.1
Name: center-tk-window
Version: 1.0.0
Summary: Functions for centering tkinter windows on parent or on screen
Home-page: https://github.com/jarikmarwede/center-tk-window
Author: Jarik Marwede
Author-email: jarikmarwede@zoho.eu
License: UNKNOWN
Platform: UNKNOWN
Classifier: Programming Language :: Python :: 3.6
Classifier: Programming Language :: Python :: 3.7
Classifier: Programming Language :: Python :: 3.8
Classifier: License :: OSI Approved :: MIT License
Classifier: Operating System :: OS Independent
